promqlpy/__init__.py
promqlpy/cli.py
promqlpy/split.py
promqlpy/version.py
promqlpy/_libpromql.cpython-39-x86_64-linux-gnu.h
promqlpy/_libpromql.cpython-39-x86_64-linux-gnu.so
promqlpy-1.0.5.dist-info/entry_points.txt
promqlpy-1.0.5.dist-info/LICENSE
promqlpy-1.0.5.dist-info/WHEEL
promqlpy-1.0.5.dist-info/METADATA
promqlpy-1.0.5.dist-info/RECORD
