Metadata-Version: 2.1
Name: promqlpy
Version: 1.0.5
Summary: Python utils for parsing PromQL/MetricsQL.
Author: laixintao
Author-email: laixintaoo@gmail.com
Requires-Python: >=3.9,<4.0
Classifier: Programming Language :: Python :: 3
Classifier: Programming Language :: Python :: 3.10
Classifier: Programming Language :: Python :: 3.9
Requires-Dist: cffi (>=1.15.1,<2.0.0)
Requires-Dist: rich (>=12.5.1,<13.0.0)
